airless/google/cloud/vertexai/__init__.py
airless/google/cloud/vertexai/hook/__init__.py
airless/google/cloud/vertexai/hook/gemini.py
airless/google/cloud/vertexai/hook/vertexai.py
airless_google_cloud_vertexai-0.3.0.dist-info/METADATA
airless_google_cloud_vertexai-0.3.0.dist-info/WHEEL
airless_google_cloud_vertexai-0.3.0.dist-info/top_level.txt
airless_google_cloud_vertexai-0.3.0.dist-info/RECORD
