Metadata-Version: 2.4
Name: airless-google-cloud-vertexai
Version: 0.3.0
Summary: Airless package to manage google cloud vertexai
License-Expression: MIT
Project-URL: Homepage, https://github.com/astercapital/airless
Project-URL: Bug Tracker, https://github.com/astercapital/airless/issues
Requires-Python: >=3.9
Requires-Dist: google-cloud-aiplatform<2.0.0,>=1.66.0
Requires-Dist: airless-core>=0.2.1
